flashon/__init__.py
flashon/__main__.py
tests/__init__.py
Flashon-1.0.8.dist-info/LICENSE.txt
Flashon-1.0.8.dist-info/METADATA
Flashon-1.0.8.dist-info/WHEEL
Flashon-1.0.8.dist-info/entry_points.txt
Flashon-1.0.8.dist-info/top_level.txt
Flashon-1.0.8.dist-info/RECORD
