Metadata-Version: 2.1
Name: Flashon
Version: 1.0.8
Summary: Build your python project or pypi, Must be in the project directory (python -m flashon)
Author: CaiqueONZZ
License-File: LICENSE.txt
